cnxepub/__init__.py
cnxepub/_version.py
cnxepub/adapters.py
cnxepub/collation.py
cnxepub/data_uri.py
cnxepub/epub.py
cnxepub/formatters.py
cnxepub/html_parsers.py
cnxepub/models.py
cnxepub/testing.py
cnxepub/utils.py
cnxepub/scripts/__init__.py
cnxepub/scripts/collated_single_html/__init__.py
cnxepub/scripts/collated_single_html/main.py
cnxepub/scripts/single_html/__init__.py
cnxepub/scripts/single_html/main.py
cnxepub/templates/__init__.py
cnxepub/templates/exercise_template.py
cnxepub/tests/__init__.py
cnxepub/tests/test_adapters.py
cnxepub/tests/test_collation.py
cnxepub/tests/test_epub.py
cnxepub/tests/test_formatters.py
cnxepub/tests/test_html_parsers.py
cnxepub/tests/test_models.py
cnxepub/tests/test_utils.py
cnxepub/tests/scripts/__init__.py
cnxepub/tests/scripts/test_collated_single_html.py
cnxepub/tests/scripts/test_single_html.py
cnx_epub-1.33.0.dist-info/LICENSE.txt
cnx_epub-1.33.0.dist-info/METADATA
cnx_epub-1.33.0.dist-info/WHEEL
cnx_epub-1.33.0.dist-info/dependency_links.txt
cnx_epub-1.33.0.dist-info/entry_points.txt
cnx_epub-1.33.0.dist-info/top_level.txt
cnx_epub-1.33.0.dist-info/RECORD
