Metadata-Version: 2.1
Name: cnx-epub
Version: 1.33.0
Summary: Library for building and paring Connexions' EPUBs.
Home-page: https://github.com/connexions/cnx-epub
Author: Connexions team
Author-email: info@cnx.org
License: AGPL, See also LICENSE.txt
License-File: LICENSE.txt
Requires-Dist: jinja2
Requires-Dist: lxml (==4.4.3)
Requires-Dist: requests
Requires-Dist: python-memcached
Provides-Extra: collation
Requires-Dist: cnx-easybake ; extra == 'collation'
Provides-Extra: test
Requires-Dist: cnx-easybake ; extra == 'test'
